heartFEM/__init__.py
heartFEM/heartParameters.py
heartFEM/lcleeHeart/NashPanfilov2D.py
heartFEM/lcleeHeart/__init__.py
heartFEM/lcleeHeart/addfiber_matid.py
heartFEM/lcleeHeart/forms.py
heartFEM/lcleeHeart/forms_shavik.py
heartFEM/lcleeHeart/nsolver.py
heartFEM/lcleeHeart/rotateUGrid_w_axis.py
heartFEM/lcleeHeart/simpleActiveMaterial.py
heartFEM/lcleeHeart/vtk_py/BiV.geo
heartFEM/lcleeHeart/vtk_py/CreateVertexFromPoint.py
heartFEM/lcleeHeart/vtk_py/LV.geo
heartFEM/lcleeHeart/vtk_py/Set4ChamberDirection.py
heartFEM/lcleeHeart/vtk_py/SetBiVFiber.py
heartFEM/lcleeHeart/vtk_py/SetBiVFiber_J.py
heartFEM/lcleeHeart/vtk_py/SetBiVFiber_Quad.py
heartFEM/lcleeHeart/vtk_py/SetBiVFiber_Quad_PyQ.py
heartFEM/lcleeHeart/vtk_py/SlerpTestJ.py
heartFEM/lcleeHeart/vtk_py/__init__.py
heartFEM/lcleeHeart/vtk_py/addFieldPrincipalDirections.py
heartFEM/lcleeHeart/vtk_py/addLVfiber.py
heartFEM/lcleeHeart/vtk_py/addLocalCylindricalDirections.py
heartFEM/lcleeHeart/vtk_py/addLocalFiberOrientation.py
heartFEM/lcleeHeart/vtk_py/addLocalFiberOrientation2.py
heartFEM/lcleeHeart/vtk_py/addLocalFiberOrientation_infarct.py
heartFEM/lcleeHeart/vtk_py/addLocalProlateSpheroidalDirections.py
heartFEM/lcleeHeart/vtk_py/addMappingFromPointsToCells.py
heartFEM/lcleeHeart/vtk_py/addSystolicStrains.py
heartFEM/lcleeHeart/vtk_py/clean_pdata.py
heartFEM/lcleeHeart/vtk_py/clipDomainForCutLVMesh.py
heartFEM/lcleeHeart/vtk_py/clipSurfacesForCutLVMesh.py
heartFEM/lcleeHeart/vtk_py/clipSurfacesForCutLVMesh_PLY.py
heartFEM/lcleeHeart/vtk_py/clipSurfacesForFullLVMesh.py
heartFEM/lcleeHeart/vtk_py/clipheart.py
heartFEM/lcleeHeart/vtk_py/computeLVthickness.py
heartFEM/lcleeHeart/vtk_py/computeRegionsForBiV.py
heartFEM/lcleeHeart/vtk_py/computeVolume.py
heartFEM/lcleeHeart/vtk_py/compute_surface_strain.py
heartFEM/lcleeHeart/vtk_py/convertAbaqusMeshToUGrid.py
heartFEM/lcleeHeart/vtk_py/convertCellDataToXML.py
heartFEM/lcleeHeart/vtk_py/convertPDataToXMLMesh.py
heartFEM/lcleeHeart/vtk_py/convertQuadDataToVTK.py
heartFEM-3.6.3.dist-info/LICENSE
heartFEM-3.6.3.dist-info/METADATA
heartFEM-3.6.3.dist-info/WHEEL
heartFEM-3.6.3.dist-info/top_level.txt
heartFEM-3.6.3.dist-info/RECORD
