Metadata-Version: 2.1
Name: heartFEM
Version: 3.6.3
Summary: Optimization of patient specific heart model with myocardium FEM and cardiovascular network Windkessel.
Home-page: https://github.com/WeiXuanChan/heartFEM
Author: Wei Xuan Chan
Author-email: w.x.chan1986@gmail.com
License: MIT
Download-URL: https://github.com/WeiXuanChan/heartFEM/archive/v3.6.3.tar.gz
Keywords: medical,cardiac
Platform: UNKNOWN
Classifier: Development Status :: 5 - Production/Stable
Classifier: Intended Audience :: Developers
Classifier: Topic :: Software Development :: Build Tools
Classifier: License :: OSI Approved :: MIT License
Classifier: Programming Language :: Python :: 3.6
Classifier: Programming Language :: Python :: 3.7
Requires-Dist: numpy
Requires-Dist: matplotlib
Requires-Dist: scipy
Provides-Extra: circuit_analysis
Requires-Dist: ngspice ; extra == 'circuit_analysis'
Provides-Extra: data_storage_and_processing
Requires-Dist: vtk ; extra == 'data_storage_and_processing'
Provides-Extra: fem_analysis_software
Requires-Dist: fenics ; extra == 'fem_analysis_software'
